igwn_alert/__init__.py
igwn_alert/client.py
igwn_alert/exceptions.py
igwn_alert/tool.py
igwn_alert/version.py
igwn_alert/tests/__init__.py
igwn_alert/tests/conftest.py
igwn_alert/tests/test_igwn_alert.py
igwn_alert-0.7.0.dist-info/COPYING
igwn_alert-0.7.0.dist-info/METADATA
igwn_alert-0.7.0.dist-info/WHEEL
igwn_alert-0.7.0.dist-info/entry_points.txt
igwn_alert-0.7.0.dist-info/top_level.txt
igwn_alert-0.7.0.dist-info/RECORD
